{
  "Databases": {

    "AuthDatabase": "Server=127.0.0.1;Database=auth;Uid=Helnesis;Pwd=helnesis;",

    "CharacterDatabase": "Server=127.0.0.1;Database=characters;Uid=Helnesis;Pwd=helnesis;",

    "WorldDatabase": "Server=127.0.0.1;Database=world;Uid=Helnesis;Pwd=helnesis;",

    "HotfixesDatabase": "Server=127.0.0.1;Database=hotfixes;Uid=Helnesis;Pwd=helnesis;"
  },
  
  "IO": {
    "OutputPath": "./output/"
  },
  
  "Entities": [
    "item",
    "item_appearance",
    "item_modified_appearance",
    "item_modified_appearance_extra",
    "item_name_description",
    "item_name_description_locale",
    "item_sparse_locale",
    "item_sparse"
  ],
  
  "DB2": [
    "Achievement.db2",
    "Achievement_Category.db2",
    "ActionBarGroup.db2",
    "ActionBarGroupEntry.db2",
    "AdventureJournal.db2",
    "AdventureJournalItem.db2",
    "AdventureMapPOI.db2",
    "AlliedRace.db2",
    "AltMinimap.db2",
    "AltMinimapFiledata.db2",
    "AltMinimapWMO.db2",
    "AnimaCable.db2",
    "AnimaCylinder.db2",
    "AnimaMaterial.db2",
    "AnimationData.db2",
    "AnimKit.db2",
    "AnimKitBoneSet.db2",
    "AnimKitBoneSetAlias.db2",
    "AnimKitConfig.db2",
    "AnimKitConfigBoneSet.db2",
    "AnimKitPriority.db2",
    "AnimKitReplacement.db2",
    "AnimKitSegment.db2",
    "AnimReplacement.db2",
    "AnimReplacementSet.db2",
    "AreaConditionalData.db2",
    "AreaFarClipOverride.db2",
    "AreaGroupMember.db2",
    "AreaPOI.db2",
    "AreaPOIState.db2",
    "AreaPOIUiWidgetSet.db2",
    "AreaTable.db2",
    "AreaTrigger.db2",
    "AreaTriggerActionSet.db2",
    "AreaTriggerBoundedPlane.db2",
    "AreaTriggerBox.db2",
    "AreaTriggerCreateProperties.db2",
    "AreaTriggerCylinder.db2",
    "AreaTriggerDisk.db2",
    "AreaTriggerSphere.db2",
    "ArenaTrackedItem.db2",
    "ArmorLocation.db2",
    "Artifact.db2",
    "ArtifactAppearance.db2",
    "ArtifactAppearanceSet.db2",
    "ArtifactCategory.db2",
    "ArtifactItemToTransmog.db2",
    "ArtifactPower.db2",
    "ArtifactPowerLink.db2",
    "ArtifactPowerPicker.db2",
    "ArtifactPowerRank.db2",
    "ArtifactQuestXP.db2",
    "ArtifactTier.db2",
    "ArtifactUnlock.db2",
    "AuctionHouse.db2",
    "AuctionHouseCategory.db2",
    "AzeriteEmpoweredItem.db2",
    "AzeriteEssence.db2",
    "AzeriteEssencePower.db2",
    "AzeriteItem.db2",
    "AzeriteItemMilestonePower.db2",
    "AzeriteKnowledgeMultiplier.db2",
    "AzeriteLevelInfo.db2",
    "AzeritePower.db2",
    "AzeritePowerSetMember.db2",
    "AzeriteTierUnlock.db2",
    "AzeriteTierUnlockSet.db2",
    "AzeriteUnlockMapping.db2",
    "BankBagSlotPrices.db2",
    "BannedAddons.db2",
    "BarberShopStyle.db2",
    "BarrageEffect.db2",
    "BattlemasterList.db2",
    "BattlepayCurrency.db2",
    "BattlePetAbility.db2",
    "BattlePetAbilityEffect.db2",
    "BattlePetAbilityState.db2",
    "BattlePetAbilityTurn.db2",
    "BattlePetBreedQuality.db2",
    "BattlePetBreedState.db2",
    "BattlePetDisplayOverride.db2",
    "BattlePetEffectProperties.db2",
    "BattlePetNPCTeamMember.db2",
    "BattlePetSpecies.db2",
    "BattlePetSpeciesState.db2",
    "BattlePetSpeciesXAbility.db2",
    "BattlePetSpeciesXCovenant.db2",
    "BattlePetState.db2",
    "BattlePetVisual.db2",
    "BeamEffect.db2",
    "BeckonTrigger.db2",
    "BoneWindModifierModel.db2",
    "BoneWindModifiers.db2",
    "BonusRoll.db2",
    "Bounty.db2",
    "BountySet.db2",
    "BroadcastText.db2",
    "BroadcastTextDuration.db2",
    "CameraEffect.db2",
    "CameraEffectEntry.db2",
    "CameraMode.db2",
    "Campaign.db2",
    "CampaignXCondition.db2",
    "CampaignXQuestLine.db2",
    "CastableRaidBuffs.db2",
    "CelestialBody.db2",
    "Cfg_Categories.db2",
    "Cfg_Configs.db2",
    "Cfg_Regions.db2",
    "ChallengeModeItemBonusOverride.db2",
    "CharacterFaceBoneSet.db2",
    "CharacterFacialHairStyles.db2",
    "CharacterLoadout.db2",
    "CharacterLoadoutItem.db2",
    "CharacterLoadoutPet.db2",
    "CharacterServiceInfo.db2",
    "CharBaseInfo.db2",
    "CharBaseSection.db2",
    "CharComponentTextureLayouts.db2",
    "CharComponentTextureSections.db2",
    "CharHairGeosets.db2",
    "CharSectionCondition.db2",
    "CharShipment.db2",
    "CharShipmentContainer.db2",
    "CharStartKit.db2",
    "CharStartOutfit.db2",
    "CharTitles.db2",
    "ChatChannels.db2",
    "ChatProfanity.db2",
    "ChrClasses.db2",
    "ChrClassesXPowerTypes.db2",
    "ChrClassRaceSex.db2",
    "ChrClassTitle.db2",
    "ChrClassUIChrModelInfo.db2",
    "ChrClassUIDisplay.db2",
    "ChrClassVillain.db2",
    "ChrCreateClassAnimTarget.db2",
    "ChrCreateClassAnimTargetInfo.db2",
    "ChrCustClientChoiceConversion.db2",
    "ChrCustGeoComponentLink.db2",
    "ChrCustItemGeoModify.db2",
    "ChrCustomization.db2",
    "ChrCustomizationBoneSet.db2",
    "ChrCustomizationCategory.db2",
    "ChrCustomizationChoice.db2",
    "ChrCustomizationCondModel.db2",
    "ChrCustomizationConversion.db2",
    "ChrCustomizationDisplayInfo.db2",
    "ChrCustomizationElement.db2",
    "ChrCustomizationGeoset.db2",
    "ChrCustomizationGlyphPet.db2",
    "ChrCustomizationMaterial.db2",
    "ChrCustomizationOption.db2",
    "ChrCustomizationReq.db2",
    "ChrCustomizationReqChoice.db2",
    "ChrCustomizationSkinnedModel.db2",
    "ChrCustomizationVisReq.db2",
    "ChrCustomizationVoice.db2",
    "ChrModel.db2",
    "ChrModelMaterial.db2",
    "ChrModelTextureLayer.db2",
    "ChrRaceRacialAbility.db2",
    "ChrRaces.db2",
    "ChrRacesCreateScreenIcon.db2",
    "ChrRacesPing.db2",
    "ChrRaceXChrModel.db2",
    "ChrSelectBackgroundCDI.db2",
    "ChrSpecialization.db2",
    "ChrUpgradeBucket.db2",
    "ChrUpgradeBucketSpell.db2",
    "ChrUpgradeTier.db2",
    "CinematicCamera.db2",
    "CinematicSequences.db2",
    "ClientSceneEffect.db2",
    "CloakDampening.db2",
    "CloneEffect.db2",
    "CollectableSourceEncounter.db2",
    "CollectableSourceEncounterSparse.db2",
    "CollectableSourceInfo.db2",
    "CollectableSourceQuest.db2",
    "CollectableSourceQuestSparse.db2",
    "CollectableSourceVendor.db2",
    "CollectableSourceVendorSparse.db2",
    "CombatCondition.db2",
    "CommentatorIndirectSpell.db2",
    "CommentatorStartLocation.db2",
    "CommentatorTrackedCooldown.db2",
    "CommunityIcon.db2",
    "ComponentModelFileData.db2",
    "ComponentTextureFileData.db2",
    "ConditionalChrModel.db2",
    "ConditionalContentTuning.db2",
    "ConditionalItemAppearance.db2",
    "ConfigurationWarning.db2",
    "ContentPush.db2",
    "ContentRestrictionRule.db2",
    "ContentRestrictionRuleSet.db2",
    "ContentTuning.db2",
    "ContentTuningXExpected.db2",
    "ContentTuningXLabel.db2",
    "Contribution.db2",
    "ContributionStyle.db2",
    "ContributionStyleContainer.db2",
    "ConversationLine.db2",
    "CorruptionEffects.db2",
    "Covenant.db2",
    "CraftingData.db2",
    "CraftingDataEnchantQuality.db2",
    "CraftingDataItemQuality.db2",
    "CraftingDifficulty.db2",
    "CraftingDifficultyQuality.db2",
    "CraftingOrder.db2",
    "CraftingOrderHouse.db2",
    "CraftingQuality.db2",
    "CraftingReagentEffect.db2",
    "CraftingReagentQuality.db2",
    "CraftingReagentRequirement.db2",
    "Creature.db2",
    "CreatureDifficulty.db2",
    "CreatureDifficultyTreasure.db2",
    "CreatureDisplayInfo.db2",
    "CreatureDisplayInfoCond.db2",
    "CreatureDisplayInfoCondXChoice.db2",
    "CreatureDisplayInfoEvt.db2",
    "CreatureDisplayInfoExtra.db2",
    "CreatureDisplayInfoGeosetData.db2",
    "CreatureDisplayInfoOption.db2",
    "CreatureDisplayInfoTrn.db2",
    "CreatureDisplayXUIModelScene.db2",
    "CreatureDispXUiCamera.db2",
    "CreatureFamily.db2",
    "CreatureFamilyXUIModelScene.db2",
    "CreatureImmunities.db2",
    "CreatureLabel.db2",
    "CreatureModelData.db2",
    "CreatureMovementInfo.db2",
    "CreatureSoundData.db2",
    "CreatureSoundFidget.db2",
    "CreatureType.db2",
    "CreatureXContribution.db2",
    "CreatureXDisplayInfo.db2",
    "CreatureXUiWidgetSet.db2",
    "Criteria.db2",
    "CriteriaTree.db2",
    "CriteriaTreeXEffect.db2",
    "CurrencyCategory.db2",
    "CurrencyContainer.db2",
    "CurrencyTypes.db2",
    "Curve.db2",
    "CurvePoint.db2",
    "DeathThudLookups.db2",
    "DecalProperties.db2",
    "DeclinedWord.db2",
    "DeclinedWordCases.db2",
    "DestructibleModelData.db2",
    "DeviceBlacklist.db2",
    "Difficulty.db2",
    "DisplaySeason.db2",
    "DissolveEffect.db2",
    "DriverBlacklist.db2",
    "DungeonEncounter.db2",
    "DurabilityCosts.db2",
    "DurabilityQuality.db2",
    "EdgeGlowEffect.db2",
    "Emotes.db2",
    "EmotesText.db2",
    "EmotesTextData.db2",
    "EmotesTextSound.db2",
    "EnvironmentalDamage.db2",
    "Exhaustion.db2",
    "ExpectedStat.db2",
    "ExpectedStatMod.db2",
    "ExtraAbilityInfo.db2",
    "Faction.db2",
    "FactionGroup.db2",
    "FactionTemplate.db2",
    "FlightCapability.db2",
    "FlightCapabilityXGlideEvent.db2",
    "FootprintTextures.db2",
    "FootstepTerrainLookup.db2",
    "FriendshipRepReaction.db2",
    "FriendshipReputation.db2",
    "FullScreenEffect.db2",
    "GameClockDebug.db2",
    "GameMode.db2",
    "GameObjectAnimGroupMember.db2",
    "GameObjectArtKit.db2",
    "GameObjectDiffAnimMap.db2",
    "GameObjectDisplayCondition.db2",
    "GameObjectDisplayInfo.db2",
    "GameObjectDisplayInfoXSoundKit.db2",
    "GameObjectLabel.db2",
    "GameObjects.db2",
    "GameParameter.db2",
    "GameTips.db2",
    "GarrAbility.db2",
    "GarrAbilityCategory.db2",
    "GarrAbilityEffect.db2",
    "GarrAutoCombatant.db2",
    "GarrAutoSpell.db2",
    "GarrAutoSpellEffect.db2",
    "GarrBuilding.db2",
    "GarrBuildingDoodadSet.db2",
    "GarrBuildingPlotInst.db2",
    "GarrClassSpec.db2",
    "GarrClassSpecPlayerCond.db2",
    "GarrEncounter.db2",
    "GarrEncounterSetXEncounter.db2",
    "GarrEncounterXMechanic.db2",
    "GarrFollItemSetMember.db2",
    "GarrFollower.db2",
    "GarrFollowerLevelXP.db2",
    "GarrFollowerQuality.db2",
    "GarrFollowerSetXFollower.db2",
    "GarrFollowerType.db2",
    "GarrFollowerUICreature.db2",
    "GarrFollowerXAbility.db2",
    "GarrFollSupportSpell.db2",
    "GarrItemLevelUpgradeData.db2",
    "GarrMechanic.db2",
    "GarrMechanicSetXMechanic.db2",
    "GarrMechanicType.db2",
    "GarrMission.db2",
    "GarrMissionSet.db2",
    "GarrMissionTexture.db2",
    "GarrMissionType.db2",
    "GarrMissionXEncounter.db2",
    "GarrMissionXFollower.db2",
    "GarrMssnBonusAbility.db2",
    "GarrPlot.db2",
    "GarrPlotBuilding.db2",
    "GarrPlotInstance.db2",
    "GarrPlotUICategory.db2",
    "GarrSiteLevel.db2",
    "GarrSiteLevelPlotInst.db2",
    "GarrSpecialization.db2",
    "GarrString.db2",
    "GarrTalent.db2",
    "GarrTalentCost.db2",
    "GarrTalentMapPOI.db2",
    "GarrTalentRank.db2",
    "GarrTalentRankGroupEntry.db2",
    "GarrTalentRankGroupResearchMod.db2",
    "GarrTalentResearch.db2",
    "GarrTalentSocketProperties.db2",
    "GarrTalentTree.db2",
    "GarrTalTreeXGarrTalResearch.db2",
    "GarrType.db2",
    "GarrUiAnimClassInfo.db2",
    "GarrUiAnimRaceInfo.db2",
    "GemProperties.db2",
    "GlideEvent.db2",
    "GlideEventBlendTimes.db2",
    "GlobalColor.db2",
    "GlobalCurve.db2",
    "GlobalGameContentTuning.db2",
    "GlobalPlayerCondition.db2",
    "GlobalPlayerConditionSet.db2",
    "GlobalStrings.db2",
    "GlyphBindableSpell.db2",
    "GlyphExclusiveCategory.db2",
    "GlyphProperties.db2",
    "GlyphRequiredSpec.db2",
    "GMSurveyAnswers.db2",
    "GMSurveyCurrentSurvey.db2",
    "GMSurveyQuestions.db2",
    "GMSurveySurveys.db2",
    "GossipNPCOption.db2",
    "GossipNPCOptionDisplayInfo.db2",
    "GossipXGarrTalentTrees.db2",
    "GossipXUIDisplayInfo.db2",
    "GradientEffect.db2",
    "GroundEffectDoodad.db2",
    "GroundEffectTexture.db2",
    "GroupFinderActivity.db2",
    "GroupFinderActivityGrp.db2",
    "GroupFinderActivityXPvpBracket.db2",
    "GroupFinderCategory.db2",
    "GuildColorBackground.db2",
    "GuildColorBorder.db2",
    "GuildColorEmblem.db2",
    "GuildEmblem.db2",
    "GuildPerkSpells.db2",
    "GuildShirtBackground.db2",
    "GuildShirtBorder.db2",
    "GuildTabardBackground.db2",
    "GuildTabardBorder.db2",
    "GuildTabardEmblem.db2",
    "Heirloom.db2",
    "HelmetAnimScaling.db2",
    "HelmetGeosetData.db2",
    "HighlightColor.db2",
    "HolidayDescriptions.db2",
    "HolidayNames.db2",
    "Holidays.db2",
    "Hotfixes.db2",
    "ImportPriceArmor.db2",
    "ImportPriceQuality.db2",
    "ImportPriceShield.db2",
    "ImportPriceWeapon.db2",
    "InvasionClientData.db2",
    "Item.db2",
    "ItemAppearance.db2",
    "ItemAppearanceXUiCamera.db2",
    "ItemArmorQuality.db2",
    "ItemArmorShield.db2",
    "ItemArmorTotal.db2",
    "ItemBagFamily.db2",
    "ItemBonus.db2",
    "ItemBonusList.db2",
    "ItemBonusListGroup.db2",
    "ItemBonusListGroupEntry.db2",
    "ItemBonusListLevelDelta.db2",
    "ItemBonusListWarforgeLevelDelta.db2",
    "ItemBonusSeason.db2",
    "ItemBonusSeasonBonusListGroup.db2",
    "ItemBonusSeasonUpgradeCost.db2",
    "ItemBonusSequenceSpell.db2",
    "ItemBonusTree.db2",
    "ItemBonusTreeGroupEntry.db2",
    "ItemBonusTreeNode.db2",
    "ItemChildEquipment.db2",
    "ItemClass.db2",
    "ItemCondition.db2",
    "ItemContextPickerEntry.db2",
    "ItemConversion.db2",
    "ItemConversionEntry.db2",
    "ItemCurrencyCost.db2",
    "ItemCurrencyValue.db2",
    "ItemDamageAmmo.db2",
    "ItemDamageOneHand.db2",
    "ItemDamageOneHandCaster.db2",
    "ItemDamageTwoHand.db2",
    "ItemDamageTwoHandCaster.db2",
    "ItemDisenchantLoot.db2",
    "ItemDisplayInfo.db2",
    "ItemDisplayInfoMaterialRes.db2",
    "ItemDisplayInfoModelMatRes.db2",
    "ItemEffect.db2",
    "ItemExtendedCost.db2",
    "ItemFallbackVisual.db2",
    "ItemFixup.db2",
    "ItemFixupAction.db2",
    "ItemGroupIlvlScalingEntry.db2",
    "ItemGroupSounds.db2",
    "ItemLevelSelector.db2",
    "ItemLevelSelectorQuality.db2",
    "ItemLevelSelectorQualitySet.db2",
    "ItemLimitCategory.db2",
    "ItemLimitCategoryCondition.db2",
    "ItemLogicalCost.db2",
    "ItemLogicalCostGroup.db2",
    "ItemModifiedAppearance.db2",
    "ItemModifiedAppearanceExtra.db2",
    "ItemNameDescription.db2",
    "ItemNameSlotOverride.db2",
    "ItemPetFood.db2",
    "ItemPriceBase.db2",
    "ItemRangedDisplayInfo.db2",
    "ItemRecraft.db2",
    "ItemReforge.db2",
    "ItemSalvage.db2",
    "ItemSalvageLoot.db2",
    "ItemSearchName.db2",
    "ItemSet.db2",
    "ItemSetSpell.db2",
    "ItemSparse.db2",
    "ItemSpec.db2",
    "ItemSpecOverride.db2",
    "ItemSubClass.db2",
    "ItemSubClassMask.db2",
    "ItemVisuals.db2",
    "ItemVisualsXEffect.db2",
    "ItemXBonusTree.db2",
    "ItemXItemEffect.db2",
    "JournalEncounter.db2",
    "JournalEncounterCreature.db2",
    "JournalEncounterItem.db2",
    "JournalEncounterSection.db2",
    "JournalEncounterXDifficulty.db2",
    "JournalEncounterXMapLoc.db2",
    "JournalInstance.db2",
    "JournalInstanceEntrance.db2",
    "JournalInstanceQueueLoc.db2",
    "JournalItemXDifficulty.db2",
    "JournalSectionXDifficulty.db2",
    "JournalTier.db2",
    "JournalTierXInstance.db2",
    "Keychain.db2",
    "KeystoneAffix.db2",
    "LabelXContentRestrictRuleSet.db2",
    "Languages.db2",
    "LanguageWords.db2",
    "LFGDungeonGroup.db2",
    "LFGDungeons.db2",
    "LfgDungeonsGroupingMap.db2",
    "LFGRoleRequirement.db2",
    "Light.db2",
    "LightData.db2",
    "Lightning.db2",
    "LightParams.db2",
    "LightSkybox.db2",
    "LightWorldShadow.db2",
    "LiquidMaterial.db2",
    "LiquidObject.db2",
    "LiquidType.db2",
    "LiquidTypeXTexture.db2",
    "LivingWorldObjectTemplate.db2",
    "LivingWorldObjectTemplateModel.db2",
    "LoadingScreens.db2",
    "LoadingScreenSkin.db2",
    "LoadingScreenTaxiSplines.db2",
    "Locale.db2",
    "Location.db2",
    "Lock.db2",
    "LockType.db2",
    "LookAtController.db2",
    "LoreText.db2",
    "LoreTextPublic.db2",
    "MailTemplate.db2",
    "ManagedWorldState.db2",
    "ManagedWorldStateBuff.db2",
    "ManagedWorldStateInput.db2",
    "ManifestInterfaceActionIcon.db2",
    "ManifestInterfaceData.db2",
    "ManifestInterfaceItemIcon.db2",
    "ManifestInterfaceTOCData.db2",
    "ManifestMP3.db2",
    "Map.db2",
    "MapCelestialBody.db2",
    "MapChallengeMode.db2",
    "MapDifficulty.db2",
    "MapDifficultyXCondition.db2",
    "MapLoadingScreen.db2",
    "MapRenderScale.db2",
    "MarketingPromotionsXLocale.db2",
    "Material.db2",
    "MawPower.db2",
    "MawPowerRarity.db2",
    "MCRSlotXMCRCategory.db2",
    "MinorTalent.db2",
    "MissileTargeting.db2",
    "ModelAnimCloakDampening.db2",
    "ModelFileData.db2",
    "ModelRibbonQuality.db2",
    "ModelSound.db2",
    "ModelSoundAnimEntry.db2",
    "ModelSoundEntry.db2",
    "ModelSoundOverride.db2",
    "ModelSoundOverrideName.db2",
    "ModelSoundTagEntry.db2",
    "ModifiedCraftingCategory.db2",
    "ModifiedCraftingItem.db2",
    "ModifiedCraftingReagentItem.db2",
    "ModifiedCraftingReagentSlot.db2",
    "ModifiedCraftingSpellSlot.db2",
    "ModifierTree.db2",
    "Mount.db2",
    "MountCapability.db2",
    "MountEquipment.db2",
    "MountType.db2",
    "MountTypeXCapability.db2",
    "MountXDisplay.db2",
    "MountXSpellVisualKitPicker.db2",
    "Movie.db2",
    "MovieFileData.db2",
    "MovieVariation.db2",
    "MultiStateProperties.db2",
    "MultiTransitionProperties.db2",
    "MusicOverride.db2",
    "MythicPlusSeason.db2",
    "MythicPlusSeasonRewardLevels.db2",
    "MythicPlusSeasonTrackedAffix.db2",
    "MythicPlusSeasonTrackedMap.db2",
    "NameGen.db2",
    "NamesProfanity.db2",
    "NamesReserved.db2",
    "NamesReservedLocale.db2",
    "NPCModelItemSlotDisplayInfo.db2",
    "NPCSounds.db2",
    "NumTalentsAtLevel.db2",
    "ObjectEffect.db2",
    "ObjectEffectModifier.db2",
    "ObjectEffectPackageElem.db2",
    "Occluder.db2",
    "OccluderCurtain.db2",
    "OccluderLocation.db2",
    "OccluderNode.db2",
    "OutlineEffect.db2",
    "OverrideSpellData.db2",
    "PageTextMaterial.db2",
    "PaperDollItemFrame.db2",
    "ParagonReputation.db2",
    "ParticleColor.db2",
    "Particulate.db2",
    "ParticulateSound.db2",
    "Path.db2",
    "PathEdge.db2",
    "PathNode.db2",
    "PathNodeProperty.db2",
    "PathProperty.db2",
    "PerksActivity.db2",
    "PerksActivityCondition.db2",
    "PerksActivityTag.db2",
    "PerksActivityThreshold.db2",
    "PerksActivityThresholdGroup.db2",
    "PerksActivityXHolidays.db2",
    "PerksActivityXInterval.db2",
    "PerksActivityXTag.db2",
    "PerksUITheme.db2",
    "PerksVendorCategory.db2",
    "PerksVendorItem.db2",
    "PerksVendorItemUIGroup.db2",
    "PerksVendorItemUIInfo.db2",
    "PerksVendorItemXInterval.db2",
    "Phase.db2",
    "PhaseShiftZoneSounds.db2",
    "PhaseXPhaseGroup.db2",
    "PingType.db2",
    "PlayerCondition.db2",
    "PlayerDataFlagAccount.db2",
    "PlayerDataFlagCharacter.db2",
    "Positioner.db2",
    "PositionerState.db2",
    "PositionerStateEntry.db2",
    "PowerDisplay.db2",
    "PowerType.db2",
    "PrestigeLevelInfo.db2",
    "Profession.db2",
    "ProfessionEffect.db2",
    "ProfessionEffectType.db2",
    "ProfessionPropPoints.db2",
    "ProfessionRating.db2",
    "ProfessionTrait.db2",
    "ProfessionTraitXEffect.db2",
    "ProfessionTraitXLabel.db2",
    "ProfessionXRating.db2",
    "ProfTraitPathNode.db2",
    "ProfTraitPerkNode.db2",
    "ProfTraitTree.db2",
    "ProfTraitTreeHighlight.db2",
    "PVPBracketTypes.db2",
    "PvpBrawl.db2",
    "PVPDifficulty.db2",
    "PVPItem.db2",
    "PvpRating.db2",
    "PvpScalingEffect.db2",
    "PvpScalingEffectType.db2",
    "PVPScoreboardCellInfo.db2",
    "PVPScoreboardColumnHeader.db2",
    "PVPScoreboardLayout.db2",
    "PvpSeason.db2",
    "PvpSeasonRewardLevels.db2",
    "PVPStat.db2",
    "PvpTalent.db2",
    "PvpTalentCategory.db2",
    "PvpTalentSlotUnlock.db2",
    "PvpTier.db2",
    "QuestFactionReward.db2",
    "QuestFeedbackEffect.db2",
    "QuestInfo.db2",
    "QuestLabel.db2",
    "QuestLine.db2",
    "QuestLineXQuest.db2",
    "QuestMoneyReward.db2",
    "QuestObjective.db2",
    "QuestPackageItem.db2",
    "QuestPOIBlob.db2",
    "QuestPOIPoint.db2",
    "QuestSort.db2",
    "QuestV2.db2",
    "QuestV2CliTask.db2",
    "QuestXGroupActivity.db2",
    "QuestXP.db2",
    "QuestXUIQuestDetailsTheme.db2",
    "QuestXUiWidgetSet.db2",
    "RafActivity.db2",
    "RandPropPoints.db2",
    "RecipeProgressionGroupEntry.db2",
    "RelicSlotTierRequirement.db2",
    "RelicTalent.db2",
    "RenownRewards.db2",
    "RenownRewardsPlunderstorm.db2",
    "ResearchBranch.db2",
    "ResearchField.db2",
    "ResearchProject.db2",
    "ResearchSite.db2",
    "Resistances.db2",
    "RewardPack.db2",
    "RewardPackXCurrencyType.db2",
    "RewardPackXItem.db2",
    "RibbonQuality.db2",
    "RopeEffect.db2",
    "RTPC.db2",
    "RTPCData.db2",
    "RuneforgeLegendaryAbility.db2",
    "Scenario.db2",
    "ScenarioEventEntry.db2",
    "ScenarioStep.db2",
    "SceneScript.db2",
    "SceneScriptGlobalText.db2",
    "SceneScriptPackage.db2",
    "SceneScriptPackageMember.db2",
    "SceneScriptText.db2",
    "ScheduledInterval.db2",
    "ScreenEffect.db2",
    "ScreenEffectType.db2",
    "ScreenLocation.db2",
    "SDReplacementModel.db2",
    "SeamlessSite.db2",
    "ServerMessages.db2",
    "ShadowyEffect.db2",
    "SharedString.db2",
    "SiegeableProperties.db2",
    "SkillLine.db2",
    "SkillLineAbility.db2",
    "SkillLineXTraitTree.db2",
    "SkillRaceClassInfo.db2",
    "SkySceneXPlayerCondition.db2",
    "Soulbind.db2",
    "SoulbindConduit.db2",
    "SoulbindConduitEnhancedSocket.db2",
    "SoulbindConduitItem.db2",
    "SoulbindConduitRank.db2",
    "SoulbindConduitRankProperties.db2",
    "SoulbindUIDisplayInfo.db2",
    "SoundAmbience.db2",
    "SoundAmbienceFlavor.db2",
    "SoundBus.db2",
    "SoundBusOverride.db2",
    "SoundEmitterPillPoints.db2",
    "SoundEmitters.db2",
    "SoundEnvelope.db2",
    "SoundFilter.db2",
    "SoundFilterElem.db2",
    "SoundKit.db2",
    "SoundKitAdvanced.db2",
    "SoundKitChild.db2",
    "SoundKitEntry.db2",
    "SoundKitFallback.db2",
    "SoundMixGroup.db2",
    "SoundOverride.db2",
    "SoundParameter.db2",
    "SoundProviderPreferences.db2",
    "SoundWaterfallEmitter.db2",
    "SourceInfo.db2",
    "SpamMessages.db2",
    "SpecializationSpells.db2",
    "SpecializationSpellsDisplay.db2",
    "SpecSetMember.db2",
    "Spell.db2",
    "SpellActionBarPref.db2",
    "SpellActivationOverlay.db2",
    "SpellAuraOptions.db2",
    "SpellAuraRestrictions.db2",
    "SpellAuraVisibility.db2",
    "SpellAuraVisXChrSpec.db2",
    "SpellCastingRequirements.db2",
    "SpellCastTimes.db2",
    "SpellCategories.db2",
    "SpellCategory.db2",
    "SpellChainEffects.db2",
    "SpellClassOptions.db2",
    "SpellClutterAreaEffectCounts.db2",
    "SpellClutterFrameRates.db2",
    "SpellClutterImpactModelCounts.db2",
    "SpellClutterKitDistances.db2",
    "SpellClutterMissileDist.db2",
    "SpellClutterWeaponTrailDist.db2",
    "SpellCooldowns.db2",
    "SpellDescriptionVariables.db2",
    "SpellDispelType.db2",
    "SpellDuration.db2",
    "SpellEffect.db2",
    "SpellEffectAutoDescription.db2",
    "SpellEffectEmission.db2",
    "SpellEmpower.db2",
    "SpellEmpowerStage.db2",
    "SpellEquippedItems.db2",
    "SpellFlyout.db2",
    "SpellFlyoutItem.db2",
    "SpellFocusObject.db2",
    "SpellInterrupts.db2",
    "SpellItemEnchantment.db2",
    "SpellItemEnchantmentCondition.db2",
    "SpellKeyboundOverride.db2",
    "SpellLabel.db2",
    "SpellLearnSpell.db2",
    "SpellLevels.db2",
    "SpellMechanic.db2",
    "SpellMemorizeCost.db2",
    "SpellMisc.db2",
    "SpellMissile.db2",
    "SpellMissileMotion.db2",
    "SpellName.db2",
    "SpellOverrideName.db2",
    "SpellPower.db2",
    "SpellPowerDifficulty.db2",
    "SpellProceduralEffect.db2",
    "SpellProcsPerMinute.db2",
    "SpellProcsPerMinuteMod.db2",
    "SpellRadius.db2",
    "SpellRange.db2",
    "SpellReagents.db2",
    "SpellReagentsCurrency.db2",
    "SpellReplacement.db2",
    "SpellScaling.db2",
    "SpellScript.db2",
    "SpellScriptText.db2",
    "SpellShapeshift.db2",
    "SpellShapeshiftForm.db2",
    "SpellSpecialUnitEffect.db2",
    "SpellTargetRestrictions.db2",
    "SpellTotems.db2",
    "SpellVisual.db2",
    "SpellVisualAnim.db2",
    "SpellVisualColorEffect.db2",
    "SpellVisualEffectName.db2",
    "SpellVisualEvent.db2",
    "SpellVisualKit.db2",
    "SpellVisualKitAreaModel.db2",
    "SpellVisualKitEffect.db2",
    "SpellVisualKitModelAttach.db2",
    "SpellVisualKitPicker.db2",
    "SpellVisualKitPickerEntry.db2",
    "SpellVisualMissile.db2",
    "SpellVisualScreenEffect.db2",
    "SpellXDescriptionVariables.db2",
    "SpellXSpellVisual.db2",
    "SSAOSettings.db2",
    "StartupFiles.db2",
    "Startup_Strings.db2",
    "Stationery.db2",
    "SummonProperties.db2",
    "TactKey.db2",
    "TactKeyLookup.db2",
    "Talent.db2",
    "TaxiNodes.db2",
    "TaxiPath.db2",
    "TaxiPathNode.db2",
    "TerrainColorGradingRamp.db2",
    "TerrainMaterial.db2",
    "TerrainType.db2",
    "TerrainTypeSounds.db2",
    "TextureBlendSet.db2",
    "TextureFileData.db2",
    "TierTransition.db2",
    "TotemCategory.db2",
    "Toy.db2",
    "TradeSkillCategory.db2",
    "TradeSkillItem.db2",
    "TraitCond.db2",
    "TraitCost.db2",
    "TraitCurrency.db2",
    "TraitCurrencySource.db2",
    "TraitDefinition.db2",
    "TraitDefinitionEffectPoints.db2",
    "TraitEdge.db2",
    "TraitNode.db2",
    "TraitNodeEntry.db2",
    "TraitNodeEntryXTraitCond.db2",
    "TraitNodeEntryXTraitCost.db2",
    "TraitNodeGroup.db2",
    "TraitNodeGroupXTraitCond.db2",
    "TraitNodeGroupXTraitCost.db2",
    "TraitNodeGroupXTraitNode.db2",
    "TraitNodeXTraitCond.db2",
    "TraitNodeXTraitCost.db2",
    "TraitNodeXTraitNodeEntry.db2",
    "TraitSystem.db2",
    "TraitTree.db2",
    "TraitTreeLoadout.db2",
    "TraitTreeLoadoutEntry.db2",
    "TraitTreeXTraitCost.db2",
    "TraitTreeXTraitCurrency.db2",
    "TransformMatrix.db2",
    "TransmogDefaultLevel.db2",
    "TransmogHoliday.db2",
    "TransmogIllusion.db2",
    "TransmogSet.db2",
    "TransmogSetGroup.db2",
    "TransmogSetItem.db2",
    "TransportAnimation.db2",
    "TransportPhysics.db2",
    "TransportRotation.db2",
    "Trophy.db2",
    "UIArrowCallout.db2",
    "UiCamera.db2",
    "UiCameraType.db2",
    "UiCamFbackTalkingHeadChrRace.db2",
    "UiCamFbackTransmogChrRace.db2",
    "UiCamFbackTransmogWeapon.db2",
    "UiCanvas.db2",
    "UIChromieTimeExpansionInfo.db2",
    "UICovenantAbility.db2",
    "UiCovenantDisplayInfo.db2",
    "UICovenantPreview.db2",
    "UIDeadlyDebuff.db2",
    "UIDungeonScoreRarity.db2",
    "UIEventToast.db2",
    "UIExpansionDisplayInfo.db2",
    "UIExpansionDisplayInfoIcon.db2",
    "UIGenericWidgetDisplay.db2",
    "UiItemInteraction.db2",
    "UiMap.db2",
    "UiMapArt.db2",
    "UiMapArtStyleLayer.db2",
    "UiMapArtTile.db2",
    "UiMapAssignment.db2",
    "UiMapFogOfWar.db2",
    "UiMapFogOfWarVisualization.db2",
    "UiMapGroupMember.db2",
    "UiMapLink.db2",
    "UiMapXMapArt.db2",
    "UiModelScene.db2",
    "UiModelSceneActor.db2",
    "UiModelSceneActorDisplay.db2",
    "UiModelSceneCamera.db2",
    "UIModifiedInstance.db2",
    "UiPartyPose.db2",
    "UiQuestDetailsTheme.db2",
    "UIScriptedAnimationEffect.db2",
    "UISplashScreen.db2",
    "UiTextureAtlas.db2",
    "UiTextureAtlasElement.db2",
    "UiTextureAtlasElementSliceData.db2",
    "UiTextureAtlasMember.db2",
    "UiTextureKit.db2",
    "UiWeeklyReward.db2",
    "UiWidget.db2",
    "UiWidgetConstantSource.db2",
    "UiWidgetDataSource.db2",
    "UiWidgetMap.db2",
    "UiWidgetSet.db2",
    "UiWidgetStringSource.db2",
    "UiWidgetVisTypeDataReq.db2",
    "UiWidgetVisualization.db2",
    "UiWidgetXWidgetSet.db2",
    "UnitBlood.db2",
    "UnitBloodLevels.db2",
    "UnitCondition.db2",
    "UnitPowerBar.db2",
    "Vehicle.db2",
    "VehiclePOIType.db2",
    "VehicleSeat.db2",
    "VehicleUIIndicator.db2",
    "VehicleUIIndSeat.db2",
    "Vignette.db2",
    "VignetteUiWidgetSet.db2",
    "VirtualAttachment.db2",
    "VirtualAttachmentCustomization.db2",
    "VocalUISounds.db2",
    "VoiceOverPriority.db2",
    "VolumeFogCondition.db2",
    "WaterfallData.db2",
    "WaypointEdge.db2",
    "WaypointNode.db2",
    "WaypointSafeLocs.db2",
    "WbAccessControlList.db2",
    "WeaponImpactSounds.db2",
    "WeaponSwingSounds2.db2",
    "WeaponTrail.db2",
    "WeaponTrailModelDef.db2",
    "WeaponTrailParam.db2",
    "Weather.db2",
    "WeatherXParticulate.db2",
    "WeeklyRewardChestActivityTier.db2",
    "WeeklyRewardChestThreshold.db2",
    "WindSettings.db2",
    "WMOAreaTable.db2",
    "WMOMinimapTexture.db2",
    "WorldBossLockout.db2",
    "WorldChunkSounds.db2",
    "WorldEffect.db2",
    "WorldElapsedTimer.db2",
    "WorldLayerMapSet.db2",
    "WorldMapOverlay.db2",
    "WorldMapOverlayTile.db2",
    "WorldShadow.db2",
    "WorldStateExpression.db2",
    "WorldStateZoneSounds.db2",
    "World_PVP_Area.db2",
    "ZoneIntroMusicTable.db2",
    "ZoneLight.db2",
    "ZoneLightPoint.db2",
    "ZoneMusic.db2",
    "ZoneStory.db2"
  ]
}